fobi_phonenumber/apps.py
fobi_phonenumber/fobi_form_elements.py
fobi_phonenumber/forms.py
fobi_phonenumber/__init__.py
fobi_phonenumber-0.1.0.dist-info/DESCRIPTION.rst
fobi_phonenumber-0.1.0.dist-info/METADATA
fobi_phonenumber-0.1.0.dist-info/metadata.json
fobi_phonenumber-0.1.0.dist-info/RECORD
fobi_phonenumber-0.1.0.dist-info/top_level.txt
fobi_phonenumber-0.1.0.dist-info/WHEEL
