Metadata-Version: 2.0
Name: fobi-phonenumber
Version: 0.1.0
Summary: UNKNOWN
Home-page: https://github.com/jmsfwk/fobi_phonenumber
Author: James Fenwick
Author-email: jfenwick@tecaz.com
License: GPLv2
Platform: UNKNOWN
Classifier: Development Status :: 1 - Planning
Classifier: Intended Audience::Developers
Classifier: Framework :: Django
Classifier: Framework :: Django :: 1.9
Classifier: License :: OSI Approved
Classifier: License :: OSI Approved :: GNU General Public License v2 (GPLv2)
Classifier: Natural Language :: English
Classifier: Programming Language :: Python
Requires-Dist: django-fobi (==0.6.5)
Requires-Dist: django-phonenumber-field (==1.0.0)
